genlatex/__init__.py
genlatex/convertOldStyle.py
genlatex/formatters.py
genlatex/genLatex.py
genlatex/texData.py
genlatex-0.25.dist-info/LICENSE.txt
genlatex-0.25.dist-info/METADATA
genlatex-0.25.dist-info/WHEEL
genlatex-0.25.dist-info/entry_points.txt
genlatex-0.25.dist-info/top_level.txt
genlatex-0.25.dist-info/RECORD
