Metadata-Version: 2.1
Name: genlatex
Version: 0.25
Summary: A simple template based doc generator
Home-page: https://github.com/sspickle/genlatex
Author: Steve Spicklemire
Author-email: steve@spvi.com
License: MIT
Platform: UNKNOWN
Requires-Dist: Jinja2
Requires-Dist: si-prefix
